README.rst
setup.py
double_down/__init__.py
double_down/double_down.py
double_down.egg-info/PKG-INFO
double_down.egg-info/SOURCES.txt
double_down.egg-info/dependency_links.txt
double_down.egg-info/top_level.txt
tests/__init__.py
tests/test.py