Metadata-Version: 1.0
Name: double-down
Version: 1.0.1
Summary: A silly example of a python decorator
Home-page: https://github.com/smelnicki/double_down
Author: Stephen Melnicki
Author-email: smelnicki3@gmail.com
License: MIT (See LICENSE.rst)
Keywords: sample decorators
Platform: UNKNOWN
